timeframes/__init__.py
timeframes/eval.py
timeframes/metrics.py
timeframes/prep.py
timeframes/adapters/base.py
timeframes/utils/__init__.py
timeframes/utils/eval_helpers.py
timeframes/utils/examples.py
timeframes/utils/flattening.py
timeframes/utils/plot_forecast.py
timeframes/utils/visualize_splits.py
timeframes/utils/data/air_passengers.csv
timeframes/validation/__init__.py
timeframes/validation/kfold.py
timeframes/validation/split.py
timeframes/validation/walkforward.py
timeframes-1.3.0.dist-info/licenses/LICENSE
timeframes-1.3.0.dist-info/METADATA
timeframes-1.3.0.dist-info/WHEEL
timeframes-1.3.0.dist-info/top_level.txt
timeframes-1.3.0.dist-info/RECORD
