Metadata-Version: 2.4
Name: timeframes
Version: 1.3.0
Summary: Lightweight validation framework for time series forecasting.
Author: Andrew R. Garcia
License: MIT
Project-URL: Homepage, https://github.com/andrewrgarcia/timeframes
Project-URL: Repository, https://github.com/andrewrgarcia/timeframes
Project-URL: Issues, https://github.com/andrewrgarcia/timeframes/issues
Project-URL: Documentation, https://chatgpt.com/g/g-68ec3fa47a808191afbe09cbd63ab611-timeframesgpt-v1-0
Keywords: time series,validation,backtesting,forecasting,walkforward
Classifier: Programming Language :: Python :: 3
Classifier: License :: OSI Approved :: MIT License
Classifier: Operating System :: OS Independent
Classifier: Topic :: Scientific/Engineering :: Artificial Intelligence
Classifier: Topic :: Software Development :: Libraries
Requires-Python: >=3.9
License-File: LICENSE
Requires-Dist: numpy>=1.24
Requires-Dist: pandas>=2.0
Requires-Dist: matplotlib>=3.8
Requires-Dist: scikit-learn>=1.4
Dynamic: license-file
